{".class":"MypyFile","_fullname":"mlflow.server.prometheus_exporter","future_import_flags":[],"is_partial_stub_package":false,"is_stub":false,"names":{".class":"SymbolTable","GunicornInternalPrometheusMetrics":{".class":"SymbolTableNode","kind":"Gdef","module_hidden":true,"module_public":false,"node":{".class":"Var","flags":["is_suppressed_import","is_ready","is_inferred"],"fullname":"mlflow.server.prometheus_exporter.GunicornInternalPrometheusMetrics","name":"GunicornInternalPrometheusMetrics","type":{".class":"AnyType","missing_import_name":"mlflow.server.prometheus_exporter.GunicornInternalPrometheusMetrics","source_any":null,"type_of_any":3}}},"VERSION":{".class":"SymbolTableNode","cross_ref":"mlflow.version.VERSION","kind":"Gdef","module_hidden":true,"module_public":false},"__annotations__":{".class":"SymbolTableNode","kind":"Gdef","node":{".class":"Var","flags":["is_ready"],"fullname":"mlflow.server.prometheus_exporter.__annotations__","name":"__annotations__","type":{".class":"Instance","args":["builtins.str",{".class":"AnyType","missing_import_name":null,"source_any":null,"type_of_any":6}],"type_ref":"builtins.dict"}}},"__doc__":{".class":"SymbolTableNode","kind":"Gdef","node":{".class":"Var","flags":["is_ready"],"fullname":"mlflow.server.prometheus_exporter.__doc__","name":"__doc__","type":"builtins.str"}},"__file__":{".class":"SymbolTableNode","kind":"Gdef","node":{".class":"Var","flags":["is_ready"],"fullname":"mlflow.server.prometheus_exporter.__file__","name":"__file__","type":"builtins.str"}},"__name__":{".class":"SymbolTableNode","kind":"Gdef","node":{".class":"Var","flags":["is_ready"],"fullname":"mlflow.server.prometheus_exporter.__name__","name":"__name__","type":"builtins.str"}},"__package__":{".class":"SymbolTableNode","kind":"Gdef","node":{".class":"Var","flags":["is_ready"],"fullname":"mlflow.server.prometheus_exporter.__package__","name":"__package__","type":"builtins.str"}},"activate_prometheus_exporter":{".class":"SymbolTableNode","kind":"Gdef","node":{".class":"FuncDef","abstract_status":0,"arg_kinds":[0],"arg_names":["app"],"dataclass_transform_spec":null,"flags":[],"fullname":"mlflow.server.prometheus_exporter.activate_prometheus_exporter","name":"activate_prometheus_exporter","type":null}},"request":{".class":"SymbolTableNode","cross_ref":"flask.globals.request","kind":"Gdef","module_hidden":true,"module_public":false}},"path":"C:\\Users\\Saurav\\AppData\\Local\\Programs\\Python\\Python314\\Lib\\site-packages\\mlflow\\server\\prometheus_exporter.py"}