{"data_mtime":1774954507,"dep_lines":[2,1,3,1,1],"dep_prios":[5,10,5,5,30],"dependencies":["collections.abc","textwrap","typing","builtins","abc"],"hash":"43a4b32d067a8373371c12d8a6bc88e86e68c4dd9323197e1824caa2928665a0","id":"torch.fx._compatibility","ignore_all":true,"interface_hash":"f0215286493d8d53234e3f821ebf92937531767c2e7fa2280b003c77f48325db","mtime":1774950636,"options":{"allow_redefinition":false,"allow_untyped_globals":false,"always_false":[],"always_true":[],"bazel":false,"check_untyped_defs":true,"disable_bytearray_promotion":false,"disable_error_code":[],"disable_memoryview_promotion":false,"disabled_error_codes":[],"disallow_any_decorated":false,"disallow_any_explicit":false,"disallow_any_expr":false,"disallow_any_generics":true,"disallow_any_unimported":false,"disallow_incomplete_defs":true,"disallow_subclassing_any":true,"disallow_untyped_calls":true,"disallow_untyped_decorators":true,"disallow_untyped_defs":true,"enable_error_code":[],"enabled_error_codes":[],"extra_checks":true,"follow_imports":"normal","follow_imports_for_stubs":false,"ignore_errors":false,"ignore_missing_imports":true,"implicit_optional":false,"implicit_reexport":false,"local_partial_types":false,"mypyc":false,"old_type_inference":false,"platform":"win32","plugins":[],"strict_concatenate":false,"strict_equality":true,"strict_optional":true,"warn_no_return":true,"warn_return_any":true,"warn_unreachable":true,"warn_unused_ignores":true},"path":"C:\\Users\\Saurav\\AppData\\Local\\Programs\\Python\\Python314\\Lib\\site-packages\\torch\\fx\\_compatibility.py","plugin_data":null,"size":1148,"suppressed":[],"version_id":"1.9.0"}