{"data_mtime":1774954762,"dep_lines":[31,14,17,18,23,30,37,9,10,13,28,29,32,33,34,35,36,3,8,11,12,35,1,2,4,5,7,1,1,1,1,1,1,1,1,1,1,1,1,1,1,1],"dep_prios":[5,5,5,5,5,5,5,5,5,5,5,5,5,5,5,10,5,5,5,5,5,20,10,10,5,5,10,5,20,20,20,30,30,30,30,30,30,30,30,30,30,30],"dependencies":["mlflow.models.evaluation.utils.trace","mlflow.genai.evaluation.utils","mlflow.genai.optimize.optimizers","mlflow.genai.optimize.types","mlflow.genai.optimize.util","mlflow.genai.utils.trace_utils","mlflow.utils.autologging_utils.safety","mlflow.entities.evaluation_dataset","mlflow.entities.model_registry","mlflow.genai.datasets","mlflow.genai.prompts","mlflow.genai.scorers","mlflow.prompt.constants","mlflow.telemetry.events","mlflow.telemetry.track","mlflow.utils.gorilla","mlflow.utils.annotations","concurrent.futures","mlflow.entities","mlflow.environment_variables","mlflow.exceptions","mlflow.utils","logging","uuid","contextlib","typing","mlflow","builtins","multiprocessing.reduction","pyexpat.model","pyexpat.errors","abc","mlflow.entities._mlflow_object","mlflow.entities.assessment","mlflow.entities.trace","mlflow.genai.optimize.optimizers.base","mlflow.genai.scorers.base","mlflow.telemetry","pydantic","pydantic._internal","pydantic._internal._model_construction","pydantic.main"],"hash":"78b4b6cc45368b223733325dd936b8de831bad12c2388e67c96ab0081d8db09f","id":"mlflow.genai.optimize.optimize","ignore_all":true,"interface_hash":"a3e039d67884e855d31aba8674a01968e887c62dd056032fceed328d5df168b3","mtime":1774612360,"options":{"allow_redefinition":false,"allow_untyped_globals":false,"always_false":[],"always_true":[],"bazel":false,"check_untyped_defs":true,"disable_bytearray_promotion":false,"disable_error_code":[],"disable_memoryview_promotion":false,"disabled_error_codes":[],"disallow_any_decorated":false,"disallow_any_explicit":false,"disallow_any_expr":false,"disallow_any_generics":true,"disallow_any_unimported":false,"disallow_incomplete_defs":true,"disallow_subclassing_any":true,"disallow_untyped_calls":true,"disallow_untyped_decorators":true,"disallow_untyped_defs":true,"enable_error_code":[],"enabled_error_codes":[],"extra_checks":true,"follow_imports":"normal","follow_imports_for_stubs":false,"ignore_errors":false,"ignore_missing_imports":true,"implicit_optional":false,"implicit_reexport":false,"local_partial_types":false,"mypyc":false,"old_type_inference":false,"platform":"win32","plugins":[],"strict_concatenate":false,"strict_equality":true,"strict_optional":true,"warn_no_return":true,"warn_return_any":true,"warn_unreachable":true,"warn_unused_ignores":true},"path":"C:\\Users\\Saurav\\AppData\\Local\\Programs\\Python\\Python314\\Lib\\site-packages\\mlflow\\genai\\optimize\\optimize.py","plugin_data":null,"size":14805,"suppressed":[],"version_id":"1.9.0"}