{"data_mtime":1774954762,"dep_lines":[3,4,5,12,13,14,15,22,34,1,1,1,1,1,1,1],"dep_prios":[5,5,5,5,5,5,5,5,5,5,5,20,20,20,30,30],"dependencies":["sentence_transformers.util.decorators","sentence_transformers.util.distributed","sentence_transformers.util.environment","sentence_transformers.util.file_io","sentence_transformers.util.hard_negatives","sentence_transformers.util.misc","sentence_transformers.util.retrieval","sentence_transformers.util.similarity","sentence_transformers.util.tensor","__future__","builtins","multiprocessing.reduction","pyexpat.model","pyexpat.errors","abc","typing"],"hash":"05b7a58b5ea2ffcbe5f1a5867399ce86a679ad7304eb7831144035ab602021ca","id":"sentence_transformers.util","ignore_all":true,"interface_hash":"a0fea9371e039f8f471b814ae0c40017a61e3c84a96131ef781da281eb84ac8a","mtime":1774950772,"options":{"allow_redefinition":false,"allow_untyped_globals":false,"always_false":[],"always_true":[],"bazel":false,"check_untyped_defs":true,"disable_bytearray_promotion":false,"disable_error_code":[],"disable_memoryview_promotion":false,"disabled_error_codes":[],"disallow_any_decorated":false,"disallow_any_explicit":false,"disallow_any_expr":false,"disallow_any_generics":true,"disallow_any_unimported":false,"disallow_incomplete_defs":true,"disallow_subclassing_any":true,"disallow_untyped_calls":true,"disallow_untyped_decorators":true,"disallow_untyped_defs":true,"enable_error_code":[],"enabled_error_codes":[],"extra_checks":true,"follow_imports":"normal","follow_imports_for_stubs":false,"ignore_errors":false,"ignore_missing_imports":true,"implicit_optional":false,"implicit_reexport":false,"local_partial_types":false,"mypyc":false,"old_type_inference":false,"platform":"win32","plugins":[],"strict_concatenate":false,"strict_equality":true,"strict_optional":true,"warn_no_return":true,"warn_return_any":true,"warn_unreachable":true,"warn_unused_ignores":true},"path":"C:\\Users\\Saurav\\AppData\\Local\\Programs\\Python\\Python314\\Lib\\site-packages\\sentence_transformers\\util\\__init__.py","plugin_data":null,"size":2654,"suppressed":[],"version_id":"1.9.0"}